{
  "$schema": "https://mintlify.com/docs.json",
  "name": "Wraith Protocol",
  "theme": "maple",
  "logo": {
    "dark": "/assets/images/logo-white.png",
    "light": "/assets/images/logo-black.png"
  },
  "favicon": "/assets/images/logo-black.png",
  "colors": {
    "primary": "#c6c6c7",
    "light": "#e6e1e5",
    "dark": "#767575"
  },
  "font": {
    "headings": {
      "family": "Space Grotesk",
      "weight": 600
    },
    "body": {
      "family": "Inter"
    }
  },
  "layout": "sidenav",
  "sidebar": {
    "items": "border"
  },
  "topbar": {
    "style": "default"
  },
  "rounded": "none",
  "topbarLinks": [
    {
      "name": "GitHub",
      "url": "https://github.com/wraith-protocol"
    }
  ],
  "topbarCtaButton": {
    "name": "Get API Key",
    "url": "https://usewraith.xyz"
  },
  "tabs": [
    {
      "name": "SDK",
      "url": "sdk"
    },
    {
      "name": "Guides",
      "url": "guides"
    },
    {
      "name": "API Reference",
      "url": "api-reference"
    }
  ],
  "navigation": {
    "tabs": [
      {
        "tab": "Documentation",
        "groups": [
          {
            "group": "Overview",
            "pages": ["introduction", "getting-started", "roadmap"]
          },
          {
            "group": "Architecture",
            "pages": [
              "architecture/overview",
              "architecture/chain-connectors",
              "architecture/tee"
            ]
          },
          {
            "group": "Contracts",
            "pages": ["contracts/evm", "contracts/stellar", "contracts/solana", "contracts/ckb"]
          }
        ]
      },
      {
        "tab": "SDK",
        "groups": [
          {
            "group": "SDK",
            "pages": ["sdk/overview", "sdk/agent-client"]
          },
          {
            "group": "Chain Primitives",
            "pages": ["sdk/chains/evm", "sdk/chains/stellar", "sdk/chains/solana", "sdk/chains/ckb"]
          }
        ]
      },
      {
        "tab": "Guides",
        "groups": [
          {
            "group": "Guides",
            "pages": [
              "guides/stealth-payments",
              "guides/single-chain-agent",
              "guides/multichain-agent",
              "guides/bring-your-own-model",
              "guides/privacy-best-practices"
            ]
          }
        ]
      },
      {
        "tab": "API Reference",
        "groups": [
          {
            "group": "API Reference",
            "pages": ["api-reference/endpoints", "api-reference/types"]
          }
        ]
      }
    ]
  },
  "footerSocials": {
    "github": "https://github.com/wraith-protocol"
  }
}
